Workbook
Name CurrentAge: Planner!$B$5
Name RetirementAges: OFFSET(Calculations!$B$2,0,0,COUNT(Calculations!$B$2:$B$67),1)
Name RetirementBalances: OFFSET(Calculations!$J$2,0,0,COUNT(Calculations!$B$2:$B$67),1)

Sheet Planner
A1: Desired Retirement Age | B1: 65
A4: Current Information
A5: Current Age | B5: 35
A6: Current Annual Income | B6: 70000
A7: Current Annual Expenses | B7: 50000
A8: Current Retirement Savings | B8: 30000
A10: Economic Assumptions
A11: Annual Inflation | B11: 0.03
A12: Annual Income Increase | B12: 0.04
A13: Tax Rate | B13: 0.22
A15: Risk Tolerance (Pre-Retirement) | B15: Moderate (Est. 6% Annual Return)
A18: Risk Tolerance (Post-Retirement) | B18: Conservative (Est. 4% Annual Return)
A21: ="Your retirement savings are projected to run out at age "&Support!B9 -> Your retirement savings are projected to run out at age 78

Sheet Calculations
A1: Plan Year | B1: Age | C1: Working Income | D1: Income Tax | E1: Yearly Expenditures | F1: Yearly Savings | G1: Beginning Savings Balance | H1: Earned Interest | I1: Retirement Savings Withdrawl | J1: End Savings Balance | K1: Overall Net Gain/Loss
A2: 1 | B2: =CurrentAge -> 35 | C2: =IF(B2<Planner!$B$1,Planner!$B$6,0) -> 70000 | D2: =C2*Planner!$B$13 -> 15400 | E2: =Planner!$B$7 -> 50000 | F2: =C2-D2-E2 -> 4600 | G2: =Planner!$B$8 -> 30000 | H2: =G2*IF(B2<Planner!$B$1,Support!$B$5,Support!$B$6) -> 1800 | I2: =MAX(0,-F2) -> 0 | J2: =G2+H2+F2 -> 36400 | K2: =J2-G2 -> 6400
A3: =A2+1 -> 2 | B3: =B2+1 -> 36 | C3: =IF(B3<Planner!$B$1,C2*(1+Planner!$B$12),0) -> 72800 | D3: =C3*Planner!$B$13 -> 16016 | E3: =E2*(1+Planner!$B$11) -> 51500 | F3: =C3-D3-E3 -> 5284 | G3: =J2 -> 36400 | H3: =G3*IF(B3<Planner!$B$1,Support!$B$5,Support!$B$6) -> 2184 | I3: =MAX(0,-F3) -> 0 | J3: =G3+H3+F3 -> 43868 | K3: =J3-G3 -> 7468
A4: =A3+1 -> 3 | B4: =B3+1 -> 37 | C4: =IF(B4<Planner!$B$1,C3*(1+Planner!$B$12),0) -> 75712 | D4: =C4*Planner!$B$13 -> 16656.64 | E4: =E3*(1+Planner!$B$11) -> 53045 | F4: =C4-D4-E4 -> 6010.36 | G4: =J3 -> 43868 | H4: =G4*IF(B4<Planner!$B$1,Support!$B$5,Support!$B$6) -> 2632.08 | I4: =MAX(0,-F4) -> 0 | J4: =G4+H4+F4 -> 52510.44 | K4: =J4-G4 -> 8642.44
A5: =A4+1 -> 4 | B5: =B4+1 -> 38 | C5: =IF(B5<Planner!$B$1,C4*(1+Planner!$B$12),0) -> 78740.48 | D5: =C5*Planner!$B$13 -> 17322.906 | E5: =E4*(1+Planner!$B$11) -> 54636.35 | F5: =C5-D5-E5 -> 6781.2244 | G5: =J4 -> 52510.44 | H5: =G5*IF(B5<Planner!$B$1,Support!$B$5,Support!$B$6) -> 3150.6264 | I5: =MAX(0,-F5) -> 0 | J5: =G5+H5+F5 -> 62442.291 | K5: =J5-G5 -> 9931.8508
A6: =A5+1 -> 5 | B6: =B5+1 -> 39 | C6: =IF(B6<Planner!$B$1,C5*(1+Planner!$B$12),0) -> 81890.099 | D6: =C6*Planner!$B$13 -> 18015.822 | E6: =E5*(1+Planner!$B$11) -> 56275.44 | F6: =C6-D6-E6 -> 7598.8369 | G6: =J5 -> 62442.291 | H6: =G6*IF(B6<Planner!$B$1,Support!$B$5,Support!$B$6) -> 3746.5374 | I6: =MAX(0,-F6) -> 0 | J6: =G6+H6+F6 -> 73787.665 | K6: =J6-G6 -> 11345.374
A7: =A6+1 -> 6 | B7: =B6+1 -> 40 | C7: =IF(B7<Planner!$B$1,C6*(1+Planner!$B$12),0) -> 85165.703 | D7: =C7*Planner!$B$13 -> 18736.455 | E7: =E6*(1+Planner!$B$11) -> 57963.704 | F7: =C7-D7-E7 -> 8465.5448 | G7: =J6 -> 73787.665 | H7: =G7*IF(B7<Planner!$B$1,Support!$B$5,Support!$B$6) -> 4427.2599 | I7: =MAX(0,-F7) -> 0 | J7: =G7+H7+F7 -> 86680.47 | K7: =J7-G7 -> 12892.805
A8: =A7+1 -> 7 | B8: =B7+1 -> 41 | C8: =IF(B8<Planner!$B$1,C7*(1+Planner!$B$12),0) -> 88572.331 | D8: =C8*Planner!$B$13 -> 19485.913 | E8: =E7*(1+Planner!$B$11) -> 59702.615 | F8: =C8-D8-E8 -> 9383.8036 | G8: =J7 -> 86680.47 | H8: =G8*IF(B8<Planner!$B$1,Support!$B$5,Support!$B$6) -> 5200.8282 | I8: =MAX(0,-F8) -> 0 | J8: =G8+H8+F8 -> 101265.1 | K8: =J8-G8 -> 14584.632
A9: =A8+1 -> 8 | B9: =B8+1 -> 42 | C9: =IF(B9<Planner!$B$1,C8*(1+Planner!$B$12),0) -> 92115.225 | D9: =C9*Planner!$B$13 -> 20265.349 | E9: =E8*(1+Planner!$B$11) -> 61493.693 | F9: =C9-D9-E9 -> 10356.182 | G9: =J8 -> 101265.1 | H9: =G9*IF(B9<Planner!$B$1,Support!$B$5,Support!$B$6) -> 6075.9061 | I9: =MAX(0,-F9) -> 0 | J9: =G9+H9+F9 -> 117697.19 | K9: =J9-G9 -> 16432.088
A10: =A9+1 -> 9 | B10: =B9+1 -> 43 | C10: =IF(B10<Planner!$B$1,C9*(1+Planner!$B$12),0) -> 95799.834 | D10: =C10*Planner!$B$13 -> 21075.963 | E10: =E9*(1+Planner!$B$11) -> 63338.504 | F10: =C10-D10-E10 -> 11385.366 | G10: =J9 -> 117697.19 | H10: =G10*IF(B10<Planner!$B$1,Support!$B$5,Support!$B$6) -> 7061.8314 | I10: =MAX(0,-F10) -> 0 | J10: =G10+H10+F10 -> 136144.39 | K10: =J10-G10 -> 18447.197
A11: =A10+1 -> 10 | B11: =B10+1 -> 44 | C11: =IF(B11<Planner!$B$1,C10*(1+Planner!$B$12),0) -> 99631.827 | D11: =C11*Planner!$B$13 -> 21919.002 | E11: =E10*(1+Planner!$B$11) -> 65238.659 | F11: =C11-D11-E11 -> 12474.166 | G11: =J10 -> 136144.39 | H11: =G11*IF(B11<Planner!$B$1,Support!$B$5,Support!$B$6) -> 8168.6632 | I11: =MAX(0,-F11) -> 0 | J11: =G11+H11+F11 -> 156787.22 | K11: =J11-G11 -> 20642.829
A12: =A11+1 -> 11 | B12: =B11+1 -> 45 | C12: =IF(B12<Planner!$B$1,C11*(1+Planner!$B$12),0) -> 103617.1 | D12: =C12*Planner!$B$13 -> 22795.762 | E12: =E11*(1+Planner!$B$11) -> 67195.819 | F12: =C12-D12-E12 -> 13625.519 | G12: =J11 -> 156787.22 | H12: =G12*IF(B12<Planner!$B$1,Support!$B$5,Support!$B$6) -> 9407.233 | I12: =MAX(0,-F12) -> 0 | J12: =G12+H12+F12 -> 179819.97 | K12: =J12-G12 -> 23032.752
A13: =A12+1 -> 12 | B13: =B12+1 -> 46 | C13: =IF(B13<Planner!$B$1,C12*(1+Planner!$B$12),0) -> 107761.78 | D13: =C13*Planner!$B$13 -> 23707.592 | E13: =E12*(1+Planner!$B$11) -> 69211.694 | F13: =C13-D13-E13 -> 14842.498 | G13: =J12 -> 179819.97 | H13: =G13*IF(B13<Planner!$B$1,Support!$B$5,Support!$B$6) -> 10789.198 | I13: =MAX(0,-F13) -> 0 | J13: =G13+H13+F13 -> 205451.66 | K13: =J13-G13 -> 25631.696
A14: =A13+1 -> 13 | B14: =B13+1 -> 47 | C14: =IF(B14<Planner!$B$1,C13*(1+Planner!$B$12),0) -> 112072.26 | D14: =C14*Planner!$B$13 -> 24655.896 | E14: =E13*(1+Planner!$B$11) -> 71288.044 | F14: =C14-D14-E14 -> 16128.315 | G14: =J13 -> 205451.66 | H14: =G14*IF(B14<Planner!$B$1,Support!$B$5,Support!$B$6) -> 12327.1 | I14: =MAX(0,-F14) -> 0 | J14: =G14+H14+F14 -> 233907.08 | K14: =J14-G14 -> 28455.415
... A67: =A66+1 -> 66 | B67: =B66+1 -> 100 | C67: =IF(B67<Planner!$B$1,C66*(1+Planner!$B$12),0) -> 0 | D67: =C67*Planner!$B$13 -> 0 | E67: =E66*(1+Planner!$B$11) -> 341499.14 | F67: =C67-D67-E67 -> -341499.14 | G67: =J66 -> -7938281.4 | H67: =G67*IF(B67<Planner!$B$1,Support!$B$5,Support!$B$6) -> -317531.25 | I67: =MAX(0,-F67) -> 341499.14 | J67: =G67+H67+F67 -> -8597311.8 | K67: =J67-G67 -> -659030.39

Sheet Support
A1: Conservative (Est. 4% Annual Return) | B1: 0.04
A2: Moderate (Est. 6% Annual Return) | B2: 0.06
A3: Aggressive (Est. 8% Annual Return) | B3: 0.08
A5: Pre-Retirement Investment Return | B5: =_xlfn.XLOOKUP(Planner!B15,$A$1:$A$3,$B$1:$B$3) -> 0.06
A6: Post-Retirement Investment Return | B6: =_xlfn.XLOOKUP(Planner!B18,$A$1:$A$3,$B$1:$B$3) -> 0.04
A8: Years Before Money Runs Out | B8: {=IFERROR(MATCH(TRUE,INDEX(Calculations!$J$2:$J$67<0,0),0)-1,"Not depleted")} -> 43
A9: Age When Money Runs Out | B9: =IF(ISNUMBER(B8),Planner!B5+B8,"Not depleted") -> 78

Sheet Detail
A1: Plan Year | B1: Age | C1: Working Income | D1: Income Tax | E1: Yearly Expenditures | F1: Yearly Savings | G1: Beginning Savings Balance | H1: Earned Interest | I1: Retirement Savings Withdrawl | J1: End Savings Balance | K1: Overall Net Gain/Loss
A2: 1 | B2: =CurrentAge -> 35 | C2: =IF(B2<Planner!$B$1,Planner!$B$6,0) -> 70000 | D2: =C2*Planner!$B$13 -> 15400 | E2: =Planner!$B$7 -> 50000 | F2: =C2-D2-E2 -> 4600 | G2: =Planner!$B$8 -> 30000 | H2: =G2*IF(B2<Planner!$B$1,Support!$B$5,Support!$B$6) -> 1800 | I2: =MAX(0,-F2) -> 0 | J2: =G2+H2+F2 -> 36400 | K2: =J2-G2 -> 6400
A3: =A2+1 -> 2 | B3: =B2+1 -> 36 | C3: =IF(B3<Planner!$B$1,C2*(1+Planner!$B$12),0) -> 72800 | D3: =C3*Planner!$B$13 -> 16016 | E3: =E2*(1+Planner!$B$11) -> 51500 | F3: =C3-D3-E3 -> 5284 | G3: =J2 -> 36400 | H3: =G3*IF(B3<Planner!$B$1,Support!$B$5,Support!$B$6) -> 2184 | I3: =MAX(0,-F3) -> 0 | J3: =G3+H3+F3 -> 43868 | K3: =J3-G3 -> 7468
A4: =A3+1 -> 3 | B4: =B3+1 -> 37 | C4: =IF(B4<Planner!$B$1,C3*(1+Planner!$B$12),0) -> 75712 | D4: =C4*Planner!$B$13 -> 16656.64 | E4: =E3*(1+Planner!$B$11) -> 53045 | F4: =C4-D4-E4 -> 6010.36 | G4: =J3 -> 43868 | H4: =G4*IF(B4<Planner!$B$1,Support!$B$5,Support!$B$6) -> 2632.08 | I4: =MAX(0,-F4) -> 0 | J4: =G4+H4+F4 -> 52510.44 | K4: =J4-G4 -> 8642.44
A5: =A4+1 -> 4 | B5: =B4+1 -> 38 | C5: =IF(B5<Planner!$B$1,C4*(1+Planner!$B$12),0) -> 78740.48 | D5: =C5*Planner!$B$13 -> 17322.906 | E5: =E4*(1+Planner!$B$11) -> 54636.35 | F5: =C5-D5-E5 -> 6781.2244 | G5: =J4 -> 52510.44 | H5: =G5*IF(B5<Planner!$B$1,Support!$B$5,Support!$B$6) -> 3150.6264 | I5: =MAX(0,-F5) -> 0 | J5: =G5+H5+F5 -> 62442.291 | K5: =J5-G5 -> 9931.8508
A6: =A5+1 -> 5 | B6: =B5+1 -> 39 | C6: =IF(B6<Planner!$B$1,C5*(1+Planner!$B$12),0) -> 81890.099 | D6: =C6*Planner!$B$13 -> 18015.822 | E6: =E5*(1+Planner!$B$11) -> 56275.44 | F6: =C6-D6-E6 -> 7598.8369 | G6: =J5 -> 62442.291 | H6: =G6*IF(B6<Planner!$B$1,Support!$B$5,Support!$B$6) -> 3746.5374 | I6: =MAX(0,-F6) -> 0 | J6: =G6+H6+F6 -> 73787.665 | K6: =J6-G6 -> 11345.374
A7: =A6+1 -> 6 | B7: =B6+1 -> 40 | C7: =IF(B7<Planner!$B$1,C6*(1+Planner!$B$12),0) -> 85165.703 | D7: =C7*Planner!$B$13 -> 18736.455 | E7: =E6*(1+Planner!$B$11) -> 57963.704 | F7: =C7-D7-E7 -> 8465.5448 | G7: =J6 -> 73787.665 | H7: =G7*IF(B7<Planner!$B$1,Support!$B$5,Support!$B$6) -> 4427.2599 | I7: =MAX(0,-F7) -> 0 | J7: =G7+H7+F7 -> 86680.47 | K7: =J7-G7 -> 12892.805
A8: =A7+1 -> 7 | B8: =B7+1 -> 41 | C8: =IF(B8<Planner!$B$1,C7*(1+Planner!$B$12),0) -> 88572.331 | D8: =C8*Planner!$B$13 -> 19485.913 | E8: =E7*(1+Planner!$B$11) -> 59702.615 | F8: =C8-D8-E8 -> 9383.8036 | G8: =J7 -> 86680.47 | H8: =G8*IF(B8<Planner!$B$1,Support!$B$5,Support!$B$6) -> 5200.8282 | I8: =MAX(0,-F8) -> 0 | J8: =G8+H8+F8 -> 101265.1 | K8: =J8-G8 -> 14584.632
A9: =A8+1 -> 8 | B9: =B8+1 -> 42 | C9: =IF(B9<Planner!$B$1,C8*(1+Planner!$B$12),0) -> 92115.225 | D9: =C9*Planner!$B$13 -> 20265.349 | E9: =E8*(1+Planner!$B$11) -> 61493.693 | F9: =C9-D9-E9 -> 10356.182 | G9: =J8 -> 101265.1 | H9: =G9*IF(B9<Planner!$B$1,Support!$B$5,Support!$B$6) -> 6075.9061 | I9: =MAX(0,-F9) -> 0 | J9: =G9+H9+F9 -> 117697.19 | K9: =J9-G9 -> 16432.088
A10: =A9+1 -> 9 | B10: =B9+1 -> 43 | C10: =IF(B10<Planner!$B$1,C9*(1+Planner!$B$12),0) -> 95799.834 | D10: =C10*Planner!$B$13 -> 21075.963 | E10: =E9*(1+Planner!$B$11) -> 63338.504 | F10: =C10-D10-E10 -> 11385.366 | G10: =J9 -> 117697.19 | H10: =G10*IF(B10<Planner!$B$1,Support!$B$5,Support!$B$6) -> 7061.8314 | I10: =MAX(0,-F10) -> 0 | J10: =G10+H10+F10 -> 136144.39 | K10: =J10-G10 -> 18447.197
A11: =A10+1 -> 10 | B11: =B10+1 -> 44 | C11: =IF(B11<Planner!$B$1,C10*(1+Planner!$B$12),0) -> 99631.827 | D11: =C11*Planner!$B$13 -> 21919.002 | E11: =E10*(1+Planner!$B$11) -> 65238.659 | F11: =C11-D11-E11 -> 12474.166 | G11: =J10 -> 136144.39 | H11: =G11*IF(B11<Planner!$B$1,Support!$B$5,Support!$B$6) -> 8168.6632 | I11: =MAX(0,-F11) -> 0 | J11: =G11+H11+F11 -> 156787.22 | K11: =J11-G11 -> 20642.829
A12: =A11+1 -> 11 | B12: =B11+1 -> 45 | C12: =IF(B12<Planner!$B$1,C11*(1+Planner!$B$12),0) -> 103617.1 | D12: =C12*Planner!$B$13 -> 22795.762 | E12: =E11*(1+Planner!$B$11) -> 67195.819 | F12: =C12-D12-E12 -> 13625.519 | G12: =J11 -> 156787.22 | H12: =G12*IF(B12<Planner!$B$1,Support!$B$5,Support!$B$6) -> 9407.233 | I12: =MAX(0,-F12) -> 0 | J12: =G12+H12+F12 -> 179819.97 | K12: =J12-G12 -> 23032.752
A13: =A12+1 -> 12 | B13: =B12+1 -> 46 | C13: =IF(B13<Planner!$B$1,C12*(1+Planner!$B$12),0) -> 107761.78 | D13: =C13*Planner!$B$13 -> 23707.592 | E13: =E12*(1+Planner!$B$11) -> 69211.694 | F13: =C13-D13-E13 -> 14842.498 | G13: =J12 -> 179819.97 | H13: =G13*IF(B13<Planner!$B$1,Support!$B$5,Support!$B$6) -> 10789.198 | I13: =MAX(0,-F13) -> 0 | J13: =G13+H13+F13 -> 205451.66 | K13: =J13-G13 -> 25631.696
A14: =A13+1 -> 13 | B14: =B13+1 -> 47 | C14: =IF(B14<Planner!$B$1,C13*(1+Planner!$B$12),0) -> 112072.26 | D14: =C14*Planner!$B$13 -> 24655.896 | E14: =E13*(1+Planner!$B$11) -> 71288.044 | F14: =C14-D14-E14 -> 16128.315 | G14: =J13 -> 205451.66 | H14: =G14*IF(B14<Planner!$B$1,Support!$B$5,Support!$B$6) -> 12327.1 | I14: =MAX(0,-F14) -> 0 | J14: =G14+H14+F14 -> 233907.08 | K14: =J14-G14 -> 28455.415
... A67: =A66+1 -> 66 | B67: =B66+1 -> 100 | C67: =IF(B67<Planner!$B$1,C66*(1+Planner!$B$12),0) -> 0 | D67: =C67*Planner!$B$13 -> 0 | E67: =E66*(1+Planner!$B$11) -> 341499.14 | F67: =C67-D67-E67 -> -341499.14 | G67: =J66 -> -7938281.4 | H67: =G67*IF(B67<Planner!$B$1,Support!$B$5,Support!$B$6) -> -317531.25 | I67: =MAX(0,-F67) -> 341499.14 | J67: =G67+H67+F67 -> -8597311.8 | K67: =J67-G67 -> -659030.39
